odoo/addons/product_quick_bom/README.rst
odoo/addons/product_quick_bom/__init__.py
odoo/addons/product_quick_bom/__manifest__.py
odoo/addons/product_quick_bom/i18n/ca.po
odoo/addons/product_quick_bom/i18n/de.po
odoo/addons/product_quick_bom/i18n/el_GR.po
odoo/addons/product_quick_bom/i18n/es.po
odoo/addons/product_quick_bom/i18n/es_ES.po
odoo/addons/product_quick_bom/i18n/es_MX.po
odoo/addons/product_quick_bom/i18n/eu.po
odoo/addons/product_quick_bom/i18n/fi.po
odoo/addons/product_quick_bom/i18n/fr.po
odoo/addons/product_quick_bom/i18n/fr_CH.po
odoo/addons/product_quick_bom/i18n/fr_FR.po
odoo/addons/product_quick_bom/i18n/gl.po
odoo/addons/product_quick_bom/i18n/hr.po
odoo/addons/product_quick_bom/i18n/hr_HR.po
odoo/addons/product_quick_bom/i18n/it.po
odoo/addons/product_quick_bom/i18n/lt.po
odoo/addons/product_quick_bom/i18n/nl.po
odoo/addons/product_quick_bom/i18n/nl_NL.po
odoo/addons/product_quick_bom/i18n/product_quick_bom.pot
odoo/addons/product_quick_bom/i18n/pt.po
odoo/addons/product_quick_bom/i18n/pt_BR.po
odoo/addons/product_quick_bom/i18n/ro.po
odoo/addons/product_quick_bom/i18n/ru.po
odoo/addons/product_quick_bom/i18n/sk.po
odoo/addons/product_quick_bom/i18n/sl.po
odoo/addons/product_quick_bom/i18n/tr.po
odoo/addons/product_quick_bom/i18n/tr_TR.po
odoo/addons/product_quick_bom/i18n/vi_VN.po
odoo/addons/product_quick_bom/i18n/zh_CN.po
odoo/addons/product_quick_bom/models/__init__.py
odoo/addons/product_quick_bom/models/product.py
odoo/addons/product_quick_bom/readme/CONTRIBUTORS.rst
odoo/addons/product_quick_bom/readme/DESCRIPTION.rst
odoo/addons/product_quick_bom/readme/USAGE.rst
odoo/addons/product_quick_bom/static/description/icon.png
odoo/addons/product_quick_bom/static/description/icon.svg
odoo/addons/product_quick_bom/static/description/index.html
odoo/addons/product_quick_bom/tests/__init__.py
odoo/addons/product_quick_bom/tests/test_quick_bom.py
odoo/addons/product_quick_bom/views/product_view.xml
odoo13_addon_product_quick_bom-13.0.1.0.1.dev6.dist-info/METADATA
odoo13_addon_product_quick_bom-13.0.1.0.1.dev6.dist-info/WHEEL
odoo13_addon_product_quick_bom-13.0.1.0.1.dev6.dist-info/top_level.txt
odoo13_addon_product_quick_bom-13.0.1.0.1.dev6.dist-info/RECORD
